reference_spectra/__init__.py
reference_spectra/get_spectra.py
reference_spectra/_spectra/f74113.nc
reference_spectra/_spectra/f76ref.nc
reference_spectra/_spectra/r74113.nc
reference_spectra/_spectra/sc21refw.nc
reference_spectra-0.0.1b0.dist-info/LICENSE.txt
reference_spectra-0.0.1b0.dist-info/METADATA
reference_spectra-0.0.1b0.dist-info/WHEEL
reference_spectra-0.0.1b0.dist-info/top_level.txt
reference_spectra-0.0.1b0.dist-info/RECORD
